iplotWidgets/__init__.py
iplotWidgets/_version.py
iplotWidgets/consoleWidget/__init__.py
iplotWidgets/consoleWidget/consoleWidget.py
iplotWidgets/moduleImporter/__init__.py
iplotWidgets/moduleImporter/moduleImporter.py
iplotWidgets/moduleImporter/moduleTable.py
iplotWidgets/pulseBrowser/PulseTable.py
iplotWidgets/pulseBrowser/__init__.py
iplotWidgets/pulseBrowser/pulseBrowser.py
iplotWidgets/pulseBrowser/models/PulseTableModel.py
iplotWidgets/pulseBrowser/models/__init__.py
iplotWidgets/variableBrowser/__init__.py
iplotWidgets/variableBrowser/variableBrowser.py
iplotWidgets/variableBrowser/variableTable.py
iplotWidgets/variableBrowser/variableTree.py
iplotWidgets/variableBrowser/icons/folder.svg
iplotWidgets/variableBrowser/icons/folder_close.svg
iplotWidgets/variableBrowser/icons/variable.svg
iplotWidgets/variableBrowser/models/__init__.py
iplotWidgets/variableBrowser/models/mtJsonModel.py
iplotWidgets/variableBrowser/tools/__init__.py
iplotWidgets/variableBrowser/tools/converters.py
iplotwidgets-1.3.0.post1.dist-info/METADATA
iplotwidgets-1.3.0.post1.dist-info/WHEEL
iplotwidgets-1.3.0.post1.dist-info/top_level.txt
iplotwidgets-1.3.0.post1.dist-info/RECORD
