Metadata-Version: 2.4
Name: iplotWidgets
Version: 1.3.0.post1
Summary: Library of GUI widgets for data visualization
Author-email: ITER Organization <jscabanilla@minsait.com>
Maintainer-email: Jhon Steeven Cabanilla Alvarado <jscabanilla@minsait.com>, Pablo Martin Villares <pmartin@minsait.com>, Mario Gomez Ballesteros <mgomezb@minsait.com>
License: MIT
Project-URL: Homepage, https://github.com/iplot-viz/iplotwidgets
Project-URL: Repository, https://github.com/iplot-viz/iplotwidgets.git
Project-URL: Issues, https://github.com/iplot-viz/iplotwidgets/issues
Keywords: Widgets,GUI,Search,Variable,Pulse,IMAS,CODAC
Classifier: Programming Language :: Python :: 3
Classifier: License :: OSI Approved :: MIT License
Classifier: Operating System :: OS Independent
Requires-Python: >=3.9
Requires-Dist: iplotLogging>=1.2.0
Requires-Dist: iplotDataAccess>=1.3.1
Requires-Dist: PySide6>=6.2.3
Provides-Extra: test
Requires-Dist: pytest>=6.0; extra == "test"
